mbo_utilities/__init__.py
mbo_utilities/_parsing.py
mbo_utilities/_protocols.py
mbo_utilities/_writers.py
mbo_utilities/benchmarks.py
mbo_utilities/classifier.py
mbo_utilities/cli.py
mbo_utilities/env_cache.py
mbo_utilities/file_io.py
mbo_utilities/install.py
mbo_utilities/log.py
mbo_utilities/pipeline_registry.py
mbo_utilities/preferences.py
mbo_utilities/reader.py
mbo_utilities/transfer.py
mbo_utilities/util.py
mbo_utilities/writer.py
mbo_utilities/analysis/__init__.py
mbo_utilities/analysis/_scanphase_dialog.py
mbo_utilities/analysis/cellpose.py
mbo_utilities/analysis/metrics.py
mbo_utilities/analysis/phasecorr.py
mbo_utilities/analysis/scanphase.py
mbo_utilities/arrays/__init__.py
mbo_utilities/arrays/_base.py
mbo_utilities/arrays/_registration.py
mbo_utilities/arrays/bin.py
mbo_utilities/arrays/h5.py
mbo_utilities/arrays/isoview.py
mbo_utilities/arrays/numpy.py
mbo_utilities/arrays/nwb.py
mbo_utilities/arrays/suite2p.py
mbo_utilities/arrays/tiff.py
mbo_utilities/arrays/zarr.py
mbo_utilities/arrays/features/__init__.py
mbo_utilities/arrays/features/_base.py
mbo_utilities/arrays/features/_chunks.py
mbo_utilities/arrays/features/_compression.py
mbo_utilities/arrays/features/_dim_labels.py
mbo_utilities/arrays/features/_dim_spec.py
mbo_utilities/arrays/features/_dim_tags.py
mbo_utilities/arrays/features/_display_range.py
mbo_utilities/arrays/features/_dtype.py
mbo_utilities/arrays/features/_frame_rate.py
mbo_utilities/arrays/features/_mixin.py
mbo_utilities/arrays/features/_phase_correction.py
mbo_utilities/arrays/features/_pyramid.py
mbo_utilities/arrays/features/_registration.py
mbo_utilities/arrays/features/_roi.py
mbo_utilities/arrays/features/_segmentation.py
mbo_utilities/arrays/features/_slicing.py
mbo_utilities/arrays/features/_stats.py
mbo_utilities/arrays/features/_voxel_size.py
mbo_utilities/assets/app_settings/icon.ico
mbo_utilities/assets/app_settings/icon.png
mbo_utilities/assets/docs/file_formats.md
mbo_utilities/assets/docs/gui_quickstart.md
mbo_utilities-2.5.2.dist-info/licenses/LICENSE.md
mbo_utilities-2.5.2.dist-info/METADATA
mbo_utilities-2.5.2.dist-info/WHEEL
mbo_utilities-2.5.2.dist-info/entry_points.txt
mbo_utilities-2.5.2.dist-info/top_level.txt
mbo_utilities-2.5.2.dist-info/RECORD
