Metadata-Version: 2.4
Name: mbo_utilities
Version: 2.5.2
Summary: Various utilities for the Miller Brain Observatory
License-Expression: BSD-3-Clause
Project-URL: Homepage, https://github.com/millerbrainobservatory/mbo_utilities
Project-URL: Documentation, https://millerbrainobservatory.github.io/mbo_utilities/index.html
Project-URL: Repository, https://github.com/millerbrainobservatory/mbo_utilities
Project-URL: Issues, https://github.com/MillerBrainObservatory/mbo_utilities/issues
Keywords: Microscopy,ScanImage,multiROI,Tiff
Requires-Python: <3.13,>=3.12.7
License-File: LICENSE.md
Requires-Dist: numpy<3.0,>=2.2.5
Requires-Dist: pandas
Requires-Dist: scipy
Requires-Dist: tifffile>=2025.3.30
Requires-Dist: scikit-image
Requires-Dist: zarr>=3.1.3
Requires-Dist: dask>=2025.3.0
Requires-Dist: imageio[ffmpeg]
Requires-Dist: ffmpeg-python
Requires-Dist: matplotlib>=3.10.1
Requires-Dist: seaborn>=0.13.2
Requires-Dist: opencv-python-headless
Requires-Dist: h5py
Requires-Dist: tqdm
Requires-Dist: jupyterlab>=4.2.6
Requires-Dist: ipykernel
Requires-Dist: ipywidgets<9,>=8.0.0
Requires-Dist: icecream>=2.1.4
Requires-Dist: glfw; sys_platform != "linux"
Requires-Dist: pygfx>=0.15.2
Requires-Dist: jupyter_rfb>=0.5.1
Requires-Dist: llvmlite>=0.43.0
Requires-Dist: mkl_fft>=2.0.0
Requires-Dist: mbo-fastplotlib>=0.7.3
Requires-Dist: rendercanvas<2.5,>=2.4.2
Requires-Dist: imgui-bundle>=1.92.5
Requires-Dist: pyqt6>=6.7
Requires-Dist: pyqt6-sip
Requires-Dist: qtpy
Requires-Dist: wgpu<0.29,>=0.28.1
Provides-Extra: suite2p
Requires-Dist: numba>=0.60.0; extra == "suite2p"
Requires-Dist: lbm_suite2p_python>=2.5.3; extra == "suite2p"
Requires-Dist: suite2p_mbo>=2.0.1; extra == "suite2p"
Provides-Extra: suite3d
Requires-Dist: mbo-suite3d>=0.0.7; extra == "suite3d"
Requires-Dist: cupy-cuda12x; extra == "suite3d"
Provides-Extra: rastermap
Requires-Dist: rastermap; extra == "rastermap"
Provides-Extra: napari
Requires-Dist: napari; extra == "napari"
Requires-Dist: napari-ome-zarr; extra == "napari"
Requires-Dist: napari-animation; extra == "napari"
Provides-Extra: torch
Requires-Dist: torch; extra == "torch"
Requires-Dist: torchvision; extra == "torch"
Provides-Extra: processing
Requires-Dist: mbo_utilities[rastermap,suite2p,suite3d,torch]; extra == "processing"
Provides-Extra: docs
Requires-Dist: sphinx>=6.1.3; extra == "docs"
Requires-Dist: docutils>=0.19; extra == "docs"
Requires-Dist: nbsphinx; extra == "docs"
Requires-Dist: numpydoc; extra == "docs"
Requires-Dist: ipykernel; extra == "docs"
Requires-Dist: sphinx-autodoc2; extra == "docs"
Requires-Dist: sphinx_tippy; extra == "docs"
Requires-Dist: sphinx_gallery; extra == "docs"
Requires-Dist: sphinx-togglebutton; extra == "docs"
Requires-Dist: sphinx-copybutton; extra == "docs"
Requires-Dist: sphinx_book_theme; extra == "docs"
Requires-Dist: sphinx_design; extra == "docs"
Requires-Dist: sphinxcontrib-images; extra == "docs"
Requires-Dist: sphinxcontrib-video; extra == "docs"
Requires-Dist: sphinxcontrib-bibtex; extra == "docs"
Requires-Dist: jupytext; extra == "docs"
Requires-Dist: myst_nb; extra == "docs"
Requires-Dist: pygfx>=0.14.0; extra == "docs"
Provides-Extra: all
Requires-Dist: mbo_utilities[docs,processing]; extra == "all"
Dynamic: license-file
